ts/__init__.py
ts/__main__.py
ts/cli.py
simple_timesheet-0.2.1.dist-info/LICENSE
simple_timesheet-0.2.1.dist-info/METADATA
simple_timesheet-0.2.1.dist-info/WHEEL
simple_timesheet-0.2.1.dist-info/entry_points.txt
simple_timesheet-0.2.1.dist-info/RECORD
