Metadata-Version: 2.1
Name: simple-timesheet
Version: 0.2.1
Summary: A CLI utility for adding entries to your timesheet
License: Apache 2.0
Author: Andrew Green
Author-email: agreen@ebi.ac.uk
Requires-Python: >=3.10,<4.0
Classifier: License :: Other/Proprietary License
Classifier: Programming Language :: Python :: 3
Classifier: Programming Language :: Python :: 3.10
Classifier: Programming Language :: Python :: 3.11
Requires-Dist: click (>=8.1.7,<9.0.0)
